{"af": "Chongqing", "sq": "Chongqing", "am": "\u127e\u1295\u130d\u12aa\u1295\u130d", "ar": "\u062a\u0634\u0648\u0646\u063a\u062a\u0634\u064a\u0646\u063a", "hy": "Chongqing", "az": "\u00c7\u0259ng\u0259l", "eu": "Chongqing", "be": "Chongqing", "bn": "\u099a\u0999\u0995\u09bf\u0982", "bs": "Chongqing", "bg": "\u0427\u0443\u043d\u0446\u0438\u043d", "ca": "Chongqing", "ceb": "Chongqing", "ny": "Chongqing", "zh-cn": "\u91cd\u5e86", "zh-tw": "\u91cd\u6176", "co": "Chongqing", "hr": "Chongqing", "cs": "Chongqing", "da": "Chongqing", "nl": "Chongqing", "en": "Chongqing", "eo": "Chongqing", "et": "Chongqing", "tl": "Chongqing", "fi": "Congqing", "fr": "Chongqing", "fy": "Chongqing", "gl": "Chongqing", "ka": "Chongqing", "de": "Chongqing", "el": "\u03a4\u03c3\u03bf\u03bd\u03b3\u03ba\u03ba\u03af\u03bd\u03b3\u03ba", "gu": "\u0a9a\u0ac9\u0a82\u0a97\u0a95\u0abf\u0a82\u0a97", "ht": "Chongqing", "ha": "Chongqing", "haw": "Clongqing", "iw": "\u05e6 '\u05d5\u05e0\u05d2\u05e6'\u05d9\u05e0\u05d2", "he": "\u05e6 '\u05d5\u05e0\u05d2\u05e6'\u05d9\u05e0\u05d2", "hi": "\u091a\u0942\u0902\u0917\u091a\u0940\u0902\u0917", "hmn": "Chongqing", "hu": "Chongqing", "is": "Chongqing", "ig": "Chongeqing", "id": "Chongqing", "ga": "Chongqing", "it": "Chongqing", "ja": "ch ch", "jw": "Chongqing", "kn": "\u0c9a\u0ccb\u0c82\u0c97\u0ccd\u0c95\u0cbf\u0c82\u0c97\u0ccd", "kk": "Chonging", "km": "\u1785\u17bb\u1784\u1788\u17b8\u1784", "ko": "\ucda9\uce6d", "ku": "Chongqing", "ky": "\u0427\u0443\u043d\u0446\u0438\u043d", "lo": "\u0e88\u0ec9\u0eb2\u0ea7", "la": "Chongqing", "lv": "Chongqing", "lt": "Chongqing", "lb": "Chongqing", "mk": "\u0427\u043e\u043d\u0433\u043a\u0438\u043d\u0433", "mg": "Chongqing", "ms": "Chongqing", "ml": "\u0d1a\u0d4b\u0d19\u0d4d\u0d15\u0d3f\u0d02\u0d17\u0d4d", "mt": "Chongqing", "mi": "Chongqing", "mr": "\u091a\u094b\u0902\u0917\u0915\u093f\u0902\u0917", "mn": "\u0427\u043e\u043d\u0433\u044c\u043c\u0441", "my": "chongqing", "ne": "\u091a ong \u094d\u0917\u094d\u0930\u0939", "no": "Chongqing", "or": "\u0b1a\u0b4b\u0b19\u0b4d\u0b17\u0b15\u0b3f\u0b19\u0b4d\u0b17", "ps": "\u0686\u0627\u0642\u0647", "fa": "chongqing", "pl": "Chongqing", "pt": "Chongqing", "pa": "\u0a1a\u0a4b\u0a02\u0a17\u0a15\u0a3f\u0a70\u0a17", "ro": "Chongqing", "ru": "\u0427\u0443\u043d\u0446\u0438\u043d", "sm": "Chngqing", "gd": "Chongqing", "sr": "\u0426\u0445\u043e\u043d\u0433\u043a\u0438\u043d\u0433", "st": "Chongqing", "sn": "Chongqing", "sd": "\u0686\u0646\u06af \u06aa\u0631\u06bb", "si": "\u0da0\u0ddc\u0d82\u0d9a\u0dd2\u0d82", "sk": "Chongqing", "sl": "Chongqing", "so": "Chongqing", "es": "Chongqing", "su": "Chongqing", "sw": "Chongqing", "sv": "Chongqing", "tg": "Chongqing", "ta": "\u0b9a\u0bcb\u0b99\u0bcd\u0b95\u0bbf\u0b99\u0bcd", "te": "\u0c1a\u0c3e\u0c02\u0c17\u0c4d\u0c15\u0c3f\u0c02\u0c17\u0c4d", "th": "\u0e09\u0e07\u0e0a\u0e34\u0e48\u0e07", "tr": "Chongqing", "uk": "\u0427\u0443\u043d\u0446\u0438\u043d", "ur": "\u0686\u0648\u0646\u06af\u0642\u0646\u06af", "ug": "Chongqing", "uz": "Xongqitish", "vi": "Tr\u00f9ng Kh\u00e1nh", "cy": "Chongqing", "xh": "I-chongqing", "yi": "\u05d8\u05e9\u05d0\u05b8\u05e0\u05d2\u05e7\u05d9\u05e0\u05d2", "yo": "Chongqing", "zu": "Chongqing"}