{"Dar S Salam": null, "Salam Dar S": null, "\u1325\u120d SALL": null, "\u062f\u0627\u0631 \u0625\u0633 \u0633\u0644\u0627\u0645": null, "\u0534\u0561\u0580 \u054d\u0561\u056c\u0561\u0574": null, "Dar s salam": null, "\u0414\u0430\u0440 s \u0441\u0430\u043b\u0430": null, "\u09a6\u09be\u09b0 \u098f\u09b8 \u09b8\u09be\u09b2\u09be\u09ae": null, "\u0414\u0430\u0440 \u0421\u0430\u043b\u0430\u043c": null, "DAR S SALAM": null, "Salam": null, "\u8fbe\u5c14\u8428\u62c9\u814a\u54b8": null, "\u9054\u723e\u85a9\u62c9\u81d8\u54b8": null, "Dar es Salaam": null, "Dar": null, "Dar s Salam": null, "Dars Salam": null, "\u03a3\u03b1\u03bb\u03ac\u03bc": null, "\u0aa1\u0abe\u0ab0 \u0a8f\u0ab8 \u0ab8\u0ab2\u0abe\u0aae": null, "Dar s saum": null, "\u05d3\u05d0\u05e8 \u05e1\u05dc\u05d0\u05dd": null, "\u0921\u093e\u0930 \u090f\u0938 \u0938\u0932\u093e\u092e": null, "Dar Salam": null, "DAR S\u30b5\u30e9\u30e0": null, "\u0ca6\u0cb0\u0ccd \u0c8e\u0cb8\u0ccd \u0cb8\u0cb2\u0cbe\u0cae\u0ccd": null, "\u0414\u0430\u0440 \u0421\u0430\u043c": null, "\u178a\u17b6\u179f\u17b6\u179f\u17b6\u17a1\u17b6\u17c6": null, "\u0414\u0430\u0440-\u0421\u0430\u043b\u0430\u043c": null, "DAR S Salam": null, "D\u0101rs Salam": null, "\u0414\u0430\u0440 S \u0421\u0430\u043b\u0430\u043c": null, "\u0d21\u0d3e\u0d7c \u0d0e\u0d38\u0d4d \u0d38\u0d32\u0d3e\u0d02": null, "\u0926\u0930 \u0938\u0932\u093e\u092e": null, "Dar salam": null, "dar s \u1000\u102d\u102f\u101c\u1019\u103a": null, "SAR S \u0938\u0932\u093e\u092e\u093f": null, "\u0b21\u0b3e\u0b30\u0b4d \u0b38\u0b3f \u0b38\u0b47\u0b32\u0b3e\u0b2e |": null, "\u0689\u0627\u0631 \u0633\u0644\u0627\u0645": null, "salam": null, "\u0a26\u0a30\u0a3f\u0a06 \u0a38\u0a32\u0a3e\u0a2e": null, "\u0414\u0430\u0440 S Salam": null, "Dar s Sam": null, "Salam Dar s Salam": null, "\u0414\u0430\u0440 \u0421 \u0421\u0430\u043b\u0430\u043c": null, "\u062f\u0627\u0631 \u0633\u0644\u0627\u0645": null, "\u0da9\u0dcf\u0dbb\u0dca \u0d91\u0dc3\u0dca \u0dc3\u0dbd\u0dcf\u0db8\u0dca": null, "Si Salm": null, "Darm smah": null, "\u0c21\u0c3e\u0c30\u0c4d S \u0c38\u0c32\u0c3e\u0c02": null, "\u0421\u0430\u043b\u0430\u043c \u0414\u0430\u0440": null, "\u0688\u0627\u0631 \u0627\u06cc\u0633 \u0633\u0644\u0627\u0645": null, "Dar Salm": null, "Dar s salom": null, "\u05d3\u05d0\u05b7\u05e8 \u05e1 \u05e1\u05d0\u05b7\u05dc\u05d0\u05b7\u05dd": null}