{"af": "Osaka", "sq": "Osaka", "am": "\u12a6\u1235\u12ab\u12ab", "ar": "\u0623\u0648\u0633\u0627\u0643\u0627", "hy": "\u0555\u057d\u0561\u056f\u0561", "az": "Osaka", "eu": "Osaka", "be": "\u041e\u0441\u0430\u043a\u0430", "bn": "\u0993\u09b8\u09be\u0995\u09be", "bs": "Osaka", "bg": "Osaka", "ca": "Osaka", "ceb": "Os-sa", "ny": "Osala", "zh-cn": "\u5927\u962a", "zh-tw": "\u5927\u962a", "co": "Osaka", "hr": "Osaka", "cs": "Osaka", "da": "Osaka", "nl": "Osaka", "en": "Osaka", "eo": "Osaka", "et": "Osaka", "tl": "Osaka", "fi": "Osaka", "fr": "Osaka", "fy": "Osaka", "gl": "Osaka", "ka": "\u10dd\u10e1\u10d0\u10d9\u10d0", "de": "Osaka", "el": "\u039f\u03c3\u03ac\u03ba\u03b1", "gu": "\u0a93\u0ab8\u0abe\u0a95\u0abe", "ht": "Osaka", "ha": "Osaka", "haw": "Osaka", "iw": "\u05d0\u05d5\u05e1\u05e7\u05d4", "he": "\u05d0\u05d5\u05e1\u05e7\u05d4", "hi": "\u0913\u0938\u093e\u0915\u093e", "hmn": "Tus osaka", "hu": "Osaka", "is": "Osaka", "ig": "Osaka", "id": "Osaka", "ga": "Osaka", "it": "Osaka", "ja": "\u5927\u962a", "jw": "Osaka", "kn": "\u0c92\u0cb8\u0cbe\u0c95\u0cbe", "kk": "\u041e\u0441\u0430\u0430\u043a\u0430", "km": "\u17a2\u17bc\u179f\u17b6\u1780\u17b6", "ko": "\uc624\uc0ac\uce74", "ku": "Osaka", "ky": "\u041e\u0441\u0430\u043a\u0430", "lo": "Osaka", "la": "Osaka", "lv": "Osaka", "lt": "Osaka", "lb": "Osaka", "mk": "\u041e\u0441\u0430\u043a\u0430", "mg": "Osaka", "ms": "Osaka", "ml": "\u0d12\u0d38\u0d3e\u0d15\u0d4d\u0d15", "mt": "Osaka", "mi": "Osaka", "mr": "\u0913\u0938\u093e\u0915\u093e", "mn": "Osaka", "my": "\u1021\u102d\u102f\u1006\u102c\u1000\u102c", "ne": "\u0913\u0938\u093e\u0915\u093e", "no": "Osaka", "or": "\u0b13\u0b38\u0b3e\u0b15\u0b3e", "ps": "\u0627\u0648\u0633\u06a9\u0627", "fa": "\u0627\u0648\u0632\u0627\u06a9\u0627", "pl": "Osaka", "pt": "Osaka", "pa": "\u0a13\u0a38\u0a3e\u0a15\u0a3e", "ro": "Osaka", "ru": "\u041e\u0441\u0430\u043a\u0430", "sm": "Osaka", "gd": "Osnaka", "sr": "\u041e\u0441\u0430\u043a\u0430", "st": "Osaka", "sn": "Osaka", "sd": "\u0627\u0648\u0633\u0627\u06aa\u0627", "si": "\u0d94\u0dc3\u0dcf\u0d9a\u0dcf", "sk": "Osaka", "sl": "Osaka", "so": "Osaka", "es": "Osaka", "su": "Osaka", "sw": "Osaka", "sv": "Osaka", "tg": "\u041e\u0441\u0430\u043a\u0430", "ta": "\u0b92\u0b9a\u0bbe\u0b95\u0bbe", "te": "Osaka", "th": "\u0e42\u0e2d\u0e0b\u0e32\u0e01\u0e49\u0e32", "tr": "Osaka", "uk": "\u041e\u0441\u0430\u043a\u0430", "ur": "\u0622\u0633\u06a9\u0627", "ug": "Osaka", "uz": "Osaka", "vi": "Osaka", "cy": "Osaka", "xh": "Osaka", "yi": "\u05d0\u05b8\u05e1\u05d0\u05b7\u05e7\u05d0\u05b7", "yo": "Osaka", "zu": "Osaka"}